Metadata-Version: 1.0
Name: mukeshdistributions
Version: 0.1
Summary: Gaussian and Binomial distributions
Home-page: UNKNOWN
Author: Mukesh Adhikari
Author-email: UNKNOWN
License: UNKNOWN
Platform: UNKNOWN
